{"type":"FeatureCollection","features":[{"type":"Feature","properties":{"id":78,"slug":"gelateria-capriccio","icon":"Gelateria","name":"Gelateria Capriccio","address":""},"geometry":{"type":"Point","coordinates":[8.933269,44.406243]}},{"type":"Feature","properties":{"id":96,"slug":"la-cremeria-delle-erbe","icon":"Gelateria","name":"La Cremeria delle Erbe","address":""},"geometry":{"type":"Point","coordinates":[8.932391,44.406431]}}]}